{
  "$schema": "https://mintlify.com/docs.json",
  "theme": "maple",
  "name": "Blux Service Guide",
  "colors": {
    "primary": "#006EFD",
    "light": "#07C983",
    "dark": "#15803D"
  },
  "appearance": {
    "default": "light",
    "strict": true
  },
  "favicon": "/logo/favicon.png",
  "navigation": {
    "tabs": [
      {
        "tab": "Guides",
        "groups": [
          {
            "group": "시작하기",
            "pages": [
              "0.start/index",
              "0.start/intro",
              "0.start/setting"
            ]
          },
          {
            "group": "캠페인",
            "pages": [
              "2.campaign/intro",
              "2.campaign/create",
              "2.campaign/manage",
              "2.campaign/personal_variable",
              "2.campaign/rec_message"
            ]
          },
          {
            "group": "시나리오 (유저 여정)",
            "pages": [
              "3.scenario/intro",
              "3.scenario/create"
            ]
          },
          {
            "group": "오디언스",
            "pages": [
              "4.audience/intro"
            ]
          },
          {
            "group": "분석",
            "pages": [
              "5.analytics/user_analytics",
              "5.analytics/campaign_analytics",
              "5.analytics/scenario_analytics"
            ]
          },
          {
            "group": "채널",
            "pages": [
              "6.channel/intro",
              "6.channel/kakao",
              "6.channel/app_push",
              "6.channel/sms",
              "6.channel/webhook"
            ]
          },
          {
            "group": "데이터 연동",
            "pages": [
              "7.integration/mixpanel",
              "7.integration/amplitude"
            ]
          }
        ]
      },
      {
        "tab": "Tutorial",
        "groups": [
          {
            "group": "튜토리얼",
            "pages": [
              "1.tutorials/colduser_campaign"
            ]
          }
        ]
      }
    ],
    "global": {
      "anchors": [
        {
          "anchor": "Blog",
          "href": "https://blog.blux.ai",
          "icon": "newspaper"
        }
      ]
    }
  },
  "logo": {
    "light": "/logo/dark.png",
    "dark": "/logo/white.png"
  },
  "navbar": {
    "links": [
      {
        "label": "Support",
        "href": "jeff:hi@blux.ai"
      }
    ],
    "primary": {
      "type": "button",
      "label": "Dashboard",
      "href": "https://dashboard.mintlify.com"
    }
  },
  "footer": {
    "socials": {
      "github": "https://github.com/mintlify",
      "linkedin": "https://www.linkedin.com/company/blux-ai"
    }
  }
}